<?xml version="1.0" encoding="UTF-8"?>
<?xml-stylesheet type="text/xsl" href="dbtcat1.xsl"?>

<Company>
    <Employee empid="AAAAa">
        <empname>Naveen</empname>
        <empage>34</empage>
        <empsalary>53000</empsalary>
        <empemail>123@gmail.com</empemail>
        <empphone>9909909921</empphone>
        <empdesig>Manager</empdesig>
    </Employee>


    <Employee empid="AAAAB">
        <empname>Nagu</empname>
        <empage>44</empage>
        <empsalary>54300</empsalary>
        <empemail>123@gmail.com</empemail>
        <empphone>9909909921</empphone>
        <empdesig>team</empdesig>
        
    </Employee>

    <Employee empid="AAAAC">
        <empname>Kushal</empname>
        <empage>54</empage>
        <empsalary>55000</empsalary>
        <empemail>123@gmail.com</empemail>
        <empphone>9909909921</empphone>
        <empdesig>team associate</empdesig>
    </Employee>

    <Employee empid="AAAAD">
        <empname>Naveen</empname>
        <empage>34</empage>
        <empsalary>230000</empsalary>
        <empemail>123@gmail.com</empemail>
        <empphone>9909909921</empphone>
        <empdesig>Manager</empdesig>
    </Employee>

    <Employee empid="AAAAE">
        <empname>Naveen</empname>
        <empage>39</empage>
        <empsalary>78000</empsalary>
        <empemail>123@gmail.com</empemail>
        <empphone>9909909921</empphone>
        <empdesig>Manager</empdesig>
    </Employee>
</Company>